flowpylib/__init__.py
flowpylib/analysis/__init__.py
flowpylib/analysis/bonds/__init__.py
flowpylib/analysis/bonds/bond_metrics.py
flowpylib/analysis/commodities/__init__.py
flowpylib/analysis/commodities/commodity_metrics.py
flowpylib/analysis/crypto/__init__.py
flowpylib/analysis/crypto/crypto_metrics.py
flowpylib/analysis/crypto/defi_tools.py
flowpylib/analysis/equities/__init__.py
flowpylib/analysis/equities/equity_metrics.py
flowpylib/analysis/fx/__init__.py
flowpylib/analysis/fx/fx_metrics.py
flowpylib/analysis/general/__init__.py
flowpylib/analysis/general/impact.py
flowpylib/analysis/general/metrics.py
flowpylib/analysis/geospatial/__init__.py
flowpylib/analysis/geospatial/geospatial.py
flowpylib/analysis/real_estate/__init__.py
flowpylib/analysis/real_estate/real_estate_metrics.py
flowpylib/analysis/sentiment/__init__.py
flowpylib/analysis/sentiment/sentiment_analysis.py
flowpylib/data/__init__.py
flowpylib/data/api_integration.py
flowpylib/data/loaders/__init__.py
flowpylib/data/loaders/arctic_loader.py
flowpylib/data/loaders/csv_loader.py
flowpylib/data/loaders/kdb_loader.py
flowpylib/data/loaders/mysql_loader.py
flowpylib/data/loaders/oracle_loader.py
flowpylib/data/loaders/pgsql_loader.py
flowpylib/data/loaders/sqlserver_loader.py
flowpylib/ml/__init__.py
flowpylib/ml/models.py
flowpylib/portfolio/__init__.py
flowpylib/portfolio/optimization.py
flowpylib/risk/__init__.py
flowpylib/risk/compliance.py
flowpylib/visualization/3d_visuals.py
flowpylib/visualization/__init__.py
flowpylib/visualization/bokeh_visuals.py
flowpylib/visualization/dash_app.py
flowpylib/visualization/plotly_visuals.py
flowpylib/visualization/plotter.py
flowpylib-1.2.2.dist-info/licenses/LICENSE
test/__init__.py
test/test_analysis.py
test/test_data_loaders.py
test/test_ml.py
test/test_portfolio.py
test/test_risk.py
test/test_visualization.py
flowpylib-1.2.2.dist-info/METADATA
flowpylib-1.2.2.dist-info/WHEEL
flowpylib-1.2.2.dist-info/top_level.txt
flowpylib-1.2.2.dist-info/RECORD
