Metadata-Version: 2.4
Name: flowpylib
Version: 1.2.2
Summary: Python Library for Transaction Cost Analysis and Market Simulation
Home-page: https://github.com/jialuechen/flowpylib
Author: Jialue Chen
Author-email: jialuechen@outlook.com
License-File: LICENSE
Requires-Dist: ollama
Requires-Dist: pandas
Requires-Dist: matplotlib
Requires-Dist: plotly
Requires-Dist: bokeh
Requires-Dist: dash
Requires-Dist: flask
Requires-Dist: pybind11
Requires-Dist: numpy
Requires-Dist: geopandas
Requires-Dist: scikit-learn
Requires-Dist: textblob
Requires-Dist: requests
Requires-Dist: jax
Requires-Dist: web3
Provides-Extra: testing
Requires-Dist: pytest; extra == "testing"
Requires-Dist: pytest-cov; extra == "testing"
Dynamic: author
Dynamic: author-email
Dynamic: home-page
Dynamic: license-file
Dynamic: requires-dist
Dynamic: summary
